{
    "DEFAULT": {
        "adx_threshold": 20.0,
        "tp_ratio": 1.5,
        "sl_ratio": 1.0
    },
    "BTC/USDT": {
        "adx_threshold": 30.0,
        "tp_ratio": 2.5,
        "sl_ratio": 1.0,
        "risk_multiplier": 1.0
    },
    "ETH/USDT": {
        "adx_threshold": 15.0,
        "tp_ratio": 1.5,
        "sl_ratio": 1.0,
        "risk_multiplier": 1.0
    },
    "SOL/USDT": {
        "adx_threshold": 28.5,
        "tp_ratio": 2.5,
        "sl_ratio": 1.0,
        "risk_multiplier": 1.0
    },
    "POL/USDT": {
        "adx_threshold": 35.0,
        "tp_ratio": 2.5,
        "sl_ratio": 1.0,
        "risk_multiplier": 0.2
    },
    "ADA/USDT": {
        "adx_threshold": 20.0,
        "tp_ratio": 1.5,
        "sl_ratio": 1.0
    },
    "DOT/USDT": {
        "adx_threshold": 30.0,
        "tp_ratio": 2.5,
        "sl_ratio": 1.0,
        "risk_multiplier": 1.0
    },
    "LINK/USDT": {
        "adx_threshold": 27.0,
        "tp_ratio": 2.5,
        "sl_ratio": 1.0,
        "risk_multiplier": 1.0
    },
    "UNI/USDT": {
        "adx_threshold": 20.0,
        "tp_ratio": 1.5,
        "sl_ratio": 1.0
    },
    "AVAX/USDT": {
        "adx_threshold": 30.0,
        "tp_ratio": 2.5,
        "sl_ratio": 1.0,
        "risk_multiplier": 1.0
    },
    "XRP/USDT": {
        "adx_threshold": 30.0,
        "tp_ratio": 2.5,
        "sl_ratio": 1.0,
        "risk_multiplier": 1.0
    },
    "LTC/USDT": {
        "adx_threshold": 30.0,
        "tp_ratio": 2.5,
        "sl_ratio": 1.0,
        "risk_multiplier": 1.0
    },
    "BCH/USDT": {
        "adx_threshold": 30.0,
        "tp_ratio": 2.5,
        "sl_ratio": 1.0,
        "risk_multiplier": 1.0
    },
    "ATOM/USDT": {
        "adx_threshold": 15.0,
        "tp_ratio": 1.8000000000000003,
        "sl_ratio": 1.0,
        "risk_multiplier": 1.0
    }
}